Metadata-Version: 2.1
Name: oneNeuron-pypi-c17hawke
Version: 0.0.2
Summary: its an implimentation of Perceptron
Home-page: https://github.com/c17hawke/oneNeuron_pypi
Author: c17hawke
Author-email: sunny.c17hawke@gmail.com
License: UNKNOWN
Project-URL: Bug Tracker, https://github.com/c17hawke/oneNeuron_pypi/issues
Platform: UNKNOWN
Classifier: Programming Language :: Python :: 3
Classifier: License :: OSI Approved :: MIT License
Classifier: Operating System :: OS Independent
Requires-Python: >=3.7
License-File: LICENSE
Requires-Dist: numpy
Requires-Dist: tqdm
